README.rst
setup.py
genestation/__init__.py
genestation/genestation.py
genestation.egg-info/PKG-INFO
genestation.egg-info/SOURCES.txt
genestation.egg-info/dependency_links.txt
genestation.egg-info/top_level.txt